freeg/__init__.py
freeg/__main__.py
freeg/freeg.py
freeg/freeg_cli.py
freeg/scraper.py
freeg-0.1.1.dist-info/LICENSE
freeg-0.1.1.dist-info/METADATA
freeg-0.1.1.dist-info/WHEEL
freeg-0.1.1.dist-info/entry_points.txt
freeg-0.1.1.dist-info/top_level.txt
freeg-0.1.1.dist-info/RECORD
