Metadata-Version: 2.1
Name: freeg
Version: 0.1.1
Summary: Scrape limited free games
Home-page: https://github.com/refk32/freeg
Author: refk32
Author-email: refk32@gmail.com
License: UNKNOWN
Platform: UNKNOWN
Classifier: Programming Language :: Python :: 3
Classifier: License :: OSI Approved :: MIT License
Classifier: Operating System :: OS Independent
Classifier: Intended Audience :: Developers
Classifier: Intended Audience :: End Users/Desktop
Requires-Python: >=3.6
Requires-Dist: requests
Requires-Dist: beautifulsoup4
Requires-Dist: tldextract
Requires-Dist: colorama
Requires-Dist: lxml
